pymoso/__init__.py
pymoso/__main__.py
pymoso/chnbase.py
pymoso/chnutils.py
pymoso/cli.py
pymoso/commands/__init__.py
pymoso/commands/basecomm.py
pymoso/commands/listitems.py
pymoso/commands/solve.py
pymoso/commands/testsolve.py
pymoso/prng/__init__.py
pymoso/prng/mrg32k3a.py
pymoso/problems/__init__.py
pymoso/problems/bsprob.py
pymoso/problems/probsimpleso.py
pymoso/problems/probtpa.py
pymoso/problems/probtpb.py
pymoso/problems/probtpc.py
pymoso/solvers/__init__.py
pymoso/solvers/rminrle.py
pymoso/solvers/rpe.py
pymoso/solvers/rperle.py
pymoso/solvers/rspline.py
pymoso/testers/__init__.py
pymoso/testers/bstester.py
pymoso/testers/simplesotester.py
pymoso/testers/tpatester.py
pymoso/testers/tpbtester.py
pymoso/testers/tpctester.py
pymoso-1.0.8.dist-info/LICENSE.txt
pymoso-1.0.8.dist-info/METADATA
pymoso-1.0.8.dist-info/WHEEL
pymoso-1.0.8.dist-info/entry_points.txt
pymoso-1.0.8.dist-info/top_level.txt
pymoso-1.0.8.dist-info/RECORD
