Metadata-Version: 2.1
Name: pymoso
Version: 1.0.8
Summary: Python Multi-Objective Simulation Optimization: a package for using, implementing, and testing simulation optimization algorithms.
Home-page: https://github.com/pymoso/PyMOSO
Author: Kyle Cooper
Author-email: coope149@purdue.edu
License: UNKNOWN
Platform: UNKNOWN
Requires-Python: >=3.6.0
Requires-Dist: docopt
